tourbillon_memcached-0.4.2-py2.7-nspkg.pth
tourbillon/memcached/__init__.py
tourbillon/memcached/memcached/__init__.py
tourbillon/memcached/memcached/memcached.py
tourbillon/memcached/memcached2/__init__.py
tourbillon/memcached/memcached2/memcached.py
tourbillon_memcached-0.4.2.dist-info/DESCRIPTION.rst
tourbillon_memcached-0.4.2.dist-info/METADATA
tourbillon_memcached-0.4.2.dist-info/RECORD
tourbillon_memcached-0.4.2.dist-info/WHEEL
tourbillon_memcached-0.4.2.dist-info/metadata.json
tourbillon_memcached-0.4.2.dist-info/namespace_packages.txt
tourbillon_memcached-0.4.2.dist-info/top_level.txt
